README.txt
setup.py
CodeJam.egg-info/PKG-INFO
CodeJam.egg-info/SOURCES.txt
CodeJam.egg-info/dependency_links.txt
CodeJam.egg-info/requires.txt
CodeJam.egg-info/top_level.txt
codejam/__init__.py
codejam/graphs.py
codejam/iterators.py
codejam/maths.py