Metadata-Version: 1.0
Name: CodeJam
Version: 1.0.2
Summary: Convenience functions for Google Code Jam
Home-page: UNKNOWN
Author: Chris Knott
Author-email: chrisknott@hotmail.co.uk
License: UNKNOWN
Platform: UNKNOWN
